{
  "version": "7",
  "dialect": "postgresql",
  "entries": [
    {
      "idx": 0,
      "version": "7",
      "when": 1777278473606,
      "tag": "0000_dark_warbound",
      "breakpoints": true
    },
    {
      "idx": 1,
      "version": "7",
      "when": 1777278660321,
      "tag": "0001_romantic_glorian",
      "breakpoints": true
    },
    {
      "idx": 2,
      "version": "7",
      "when": 1777312881646,
      "tag": "0002_pagination_style",
      "breakpoints": true
    },
    {
      "idx": 3,
      "version": "7",
      "when": 1777398000000,
      "tag": "0003_glossary",
      "breakpoints": true
    },
    {
      "idx": 4,
      "version": "7",
      "when": 1777398000001,
      "tag": "0004_reader_glossary_underline",
      "breakpoints": true
    },
    {
      "idx": 5,
      "version": "7",
      "when": 1777369480731,
      "tag": "0005_glossary_hide_marker",
      "breakpoints": true
    },
    {
      "idx": 6,
      "version": "7",
      "when": 1777571200000,
      "tag": "0006_series",
      "breakpoints": true
    },
    {
      "idx": 7,
      "version": "7",
      "when": 1777680000000,
      "tag": "0007_drop_chapter_content",
      "breakpoints": true
    },
    {
      "idx": 8,
      "version": "7",
      "when": 1777689600001,
      "tag": "0008_focal_letter_color",
      "breakpoints": true
    },
    {
      "idx": 9,
      "version": "7",
      "when": 1777776000000,
      "tag": "0009_reading_sessions",
      "breakpoints": true
    }
  ]
}
